xfinity_gateway.py
xfinity_gateway-0.0.4.dist-info/LICENSE.txt
xfinity_gateway-0.0.4.dist-info/METADATA
xfinity_gateway-0.0.4.dist-info/WHEEL
xfinity_gateway-0.0.4.dist-info/top_level.txt
xfinity_gateway-0.0.4.dist-info/RECORD
