Metadata-Version: 2.1
Name: xfinity-gateway
Version: 0.0.4
Summary: Query an Xfinity Gateway
Home-page: https://github.com/cisasteelersfan/xfinity_gateway
Author: Colby Rome
Author-email: colbyrome@gmail.com
License: UNKNOWN
Platform: UNKNOWN
Classifier: Programming Language :: Python :: 3
Classifier: License :: OSI Approved :: MIT License
Classifier: Operating System :: OS Independent
Requires-Dist: requests (>=2.20)
Requires-Dist: beautifulsoup4 (>=4.0)
